README.md
setup.py
redteamcore/__init__.py
redteamcore/dictionary.py
redteamcore/log.py
redteamcore/mbox_resource.py
redteamcore/resource.py
redteamcore/resource_connector.py
redteamcore/resource_with_cache.py
redteamcore.egg-info/PKG-INFO
redteamcore.egg-info/SOURCES.txt
redteamcore.egg-info/dependency_links.txt
redteamcore.egg-info/requires.txt
redteamcore.egg-info/top_level.txt