Metadata-Version: 1.1
Name: redteamcore
Version: 0.0.1
Summary: Core Python modules for use in tooling.
Home-page: https://github.com/fedoraredteam/frtcore
Author: Kenneth Evensen
Author-email: kevensen@redhat.com
License: GPLv3
Download-URL: https://github.com/fedoraredteam/frtcore/archive/0.0.1
Keywords: frt,redteam,linux
Platform: Linux
Platform: OSX
Classifier: Development Status :: 4 - Beta
Classifier: License :: OSI Approved :: GNU General Public License v3 (GPLv3)
Classifier: Programming Language :: Python :: 2.7
